pylotus/__init__.py
pylotus/exceptions.py
pylotus/response_classes.py
pylotus/wf_api.py
tests/__init__.py
tests/test_pylotus.py
pylotus-1.0.0.dist-info/LICENSE
pylotus-1.0.0.dist-info/METADATA
pylotus-1.0.0.dist-info/WHEEL
pylotus-1.0.0.dist-info/top_level.txt
pylotus-1.0.0.dist-info/RECORD
