Metadata-Version: 2.1
Name: pylotus
Version: 1.0.0
Summary: A simple Python wrapper for the WarFrame API
Home-page: https://github.com/alex-claman/pylotus
Author: Alex Claman
Author-email: alexanderclaman@gmail.com
License: UNKNOWN
Project-URL: Bug Reports, https://github.com/alex-claman/pylotus/issues
Project-URL: Source, https://github.com/alex-claman/pylotus/
Keywords: API
Platform: UNKNOWN
Classifier: Intended Audience :: Developers
Classifier: Programming Language :: Python :: 3
Classifier: License :: OSI Approved :: MIT License
Classifier: Operating System :: OS Independent
Requires-Python: >=3.6
Requires-Dist: requests
